ifconfig_parser-0.0.1.dist-info/METADATA
ifconfig_parser-0.0.1.dist-info/RECORD
ifconfig_parser-0.0.1.dist-info/WHEEL
ifconfig_parser-0.0.1.dist-info/top_level.txt
ifconfigparser/__init__.py
ifconfigparser/ifconfig_parser.py
