Metadata-Version: 2.1
Name: ifconfig-parser
Version: 0.0.1
Summary: ifconfig-parser
Home-page: https://github.com/KnightWhoSayNi/ifconfig-parser
Author: KnightWhoSayNi
Author-email: threeheadedknight@protonmail.com
License: MIT license
Platform: UNKNOWN
Classifier: Development Status :: 4 - Beta
Classifier: Programming Language :: Python :: 3
Classifier: License :: OSI Approved :: MIT License
Classifier: Operating System :: OS Independent
Classifier: Topic :: Utilities
